{"Nodes":[],"ExecutionTime":"2023-03-03T01:52:32.0900316Z","GenerationTime":"0001-01-01T00:00:00","PluginUserSpecFlowId":"d6c26b37-d790-435e-a7a4-15a253690acc","CLIUserSpecFlowId":null,"ExecutionResults":[{"ContextType":"Scenario","FeatureFolderPath":"Features","FeatureTitle":"EditRelationship","ScenarioTitle":"Verify the max length when editing a relationship for a Name is 60 characters and Relationship is 100 characters","ScenarioArguments":[],"Status":"OK","StepResults":[{"Duration":"00:00:02.1625089","Status":"OK","Error":null,"Outputs":null},{"Duration":"00:00:00.1326584","Status":"OK","Error":null,"Outputs":null},{"Duration":"00:00:00.1204104","Status":"OK","Error":null,"Outputs":null},{"Duration":"00:00:01.2258185","Status":"OK","Error":null,"Outputs":null},{"Duration":"00:00:00.2906624","Status":"OK","Error":null,"Outputs":null},{"Duration":"00:00:00.0234084","Status":"OK","Error":null,"Outputs":null},{"Duration":"00:00:00.3053017","Status":"OK","Error":null,"Outputs":null},{"Duration":"00:00:00.0173759","Status":"OK","Error":null,"Outputs":null}],"Outputs":null}],"StepReports":null}